cloudfoundry_client/__init__.py
cloudfoundry_client/client.py
cloudfoundry_client/common_objects.py
cloudfoundry_client/doppler/__init__.py
cloudfoundry_client/doppler/client.py
cloudfoundry_client/doppler/websocket_envelope_reader.py
cloudfoundry_client/dropsonde/envelope_pb2.py
cloudfoundry_client/dropsonde/error_pb2.py
cloudfoundry_client/dropsonde/http_pb2.py
cloudfoundry_client/dropsonde/log_pb2.py
cloudfoundry_client/dropsonde/metric_pb2.py
cloudfoundry_client/dropsonde/uuid_pb2.py
cloudfoundry_client/errors.py
cloudfoundry_client/main/__init__.py
cloudfoundry_client/main/apps_command_domain.py
cloudfoundry_client/main/command_domain.py
cloudfoundry_client/main/main.py
cloudfoundry_client/main/operation_commands.py
cloudfoundry_client/main/tasks_command_domain.py
cloudfoundry_client/networking/__init__.py
cloudfoundry_client/networking/entities.py
cloudfoundry_client/networking/v1/__init__.py
cloudfoundry_client/networking/v1/external/__init__.py
cloudfoundry_client/networking/v1/external/policies.py
cloudfoundry_client/networking/v1/external/tags.py
cloudfoundry_client/operations/__init__.py
cloudfoundry_client/operations/push/__init__.py
cloudfoundry_client/operations/push/cf_ignore.py
cloudfoundry_client/operations/push/file_helper.py
cloudfoundry_client/operations/push/push.py
cloudfoundry_client/operations/push/validation/__init__.py
cloudfoundry_client/operations/push/validation/manifest.py
cloudfoundry_client/rlpgateway/__init__.py
cloudfoundry_client/rlpgateway/client.py
cloudfoundry_client/v2/__init__.py
cloudfoundry_client/v2/apps.py
cloudfoundry_client/v2/buildpacks.py
cloudfoundry_client/v2/entities.py
cloudfoundry_client/v2/events.py
cloudfoundry_client/v2/jobs.py
cloudfoundry_client/v2/resources.py
cloudfoundry_client/v2/routes.py
cloudfoundry_client/v2/service_bindings.py
cloudfoundry_client/v2/service_brokers.py
cloudfoundry_client/v2/service_instances.py
cloudfoundry_client/v2/service_keys.py
cloudfoundry_client-1.40.2.dist-info/LICENSE
cloudfoundry_client-1.40.2.dist-info/METADATA
cloudfoundry_client-1.40.2.dist-info/WHEEL
cloudfoundry_client-1.40.2.dist-info/entry_points.txt
cloudfoundry_client-1.40.2.dist-info/RECORD
